{
    "name": "obsidian generator",
    "type": "GenericCrafter",
    "description": "rapidly cools slag with cryofluid to make obsidian",
    "health": 140,
    "size": 3,
    "hasItems": true,
    "hasLiquids": true,
    "itemCapacity": 20000,
    "craftTime": 20,
    "buildCostMultiplier": 0.2,
    "consumes": {
        "power": 1,
        "liquids": [
            "slag/0.5",
        ]
	},
    "requirements": [
        "compressed-lead/50",
        "compressed-copper/75",
        "graphite/95",
    ],
    "category": "crafting",
    "research": "thorium-compressor",
    "outputItem": "obsidian/600"
}
